MANIFEST.in
README.md
requirements.txt
setup.py
li_privacy/ApiClient.py
li_privacy/DSRProcessor.py
li_privacy/DeleteProcessor.py
li_privacy/HashProcessor.py
li_privacy/InitProcessor.py
li_privacy/OptoutProcessor.py
li_privacy/PingProcessor.py
li_privacy/Request.py
li_privacy/RequestFactory.py
li_privacy/User.py
li_privacy/UserFormatError.py
li_privacy/__init__.py
li_privacy/__version__.py
li_privacy/cli.py
li_privacy.egg-info/PKG-INFO
li_privacy.egg-info/SOURCES.txt
li_privacy.egg-info/dependency_links.txt
li_privacy.egg-info/entry_points.txt
li_privacy.egg-info/requires.txt
li_privacy.egg-info/top_level.txt