Metadata-Version: 2.1
Name: li-privacy
Version: 1.2.7
Summary: CLI and sample application to interact with the LiveIntent privacy API
Home-page: https://link.liveintent.com/privacy-api
Author: Phillip Markert
Author-email: phillip@liveintent.com
License: Apache 2.0
Platform: UNKNOWN
Classifier: Operating System :: POSIX :: Linux
Classifier: License :: OSI Approved :: MIT License
Classifier: Programming Language :: Python :: 2.7
Classifier: Programming Language :: Python :: 3.5
Classifier: Programming Language :: Python :: 3.6
Classifier: Programming Language :: Python :: 3.7
Requires-Python: >=2.7, !=3.0.*, !=3.1.*, !=3.2.*, !=3.3.*, !=3.4.*
